odoo8_addon_html_text-8.0.1.0.0.99.dev3-py2.7-nspkg.pth
odoo8_addon_html_text-8.0.1.0.0.99.dev3.dist-info/DESCRIPTION.rst
odoo8_addon_html_text-8.0.1.0.0.99.dev3.dist-info/METADATA
odoo8_addon_html_text-8.0.1.0.0.99.dev3.dist-info/RECORD
odoo8_addon_html_text-8.0.1.0.0.99.dev3.dist-info/WHEEL
odoo8_addon_html_text-8.0.1.0.0.99.dev3.dist-info/metadata.json
odoo8_addon_html_text-8.0.1.0.0.99.dev3.dist-info/namespace_packages.txt
odoo8_addon_html_text-8.0.1.0.0.99.dev3.dist-info/top_level.txt
odoo_addons/html_text/README.rst
odoo_addons/html_text/__init__.py
odoo_addons/html_text/__openerp__.py
odoo_addons/html_text/i18n/html_text.pot
odoo_addons/html_text/models/__init__.py
odoo_addons/html_text/models/ir_fields_converter.py
odoo_addons/html_text/static/description/icon.png
odoo_addons/html_text/tests/__init__.py
odoo_addons/html_text/tests/test_extractor.py
