Metadata-Version: 2.0
Name: odoo8-addon-html-text
Version: 8.0.1.0.0.99.dev3
Summary: Generate excerpts from any HTML field
Home-page: https://grupoesoc.es
Author: Grupo ESOC Ingeniería de Servicios, Odoo Community Association (OCA)
Author-email: support@odoo-community.org
License: AGPL-3
Platform: UNKNOWN
Classifier: Programming Language :: Python
Classifier: Framework :: Odoo
Classifier: License :: OSI Approved :: GNU Affero General Public License v3
Requires-Python: ~=2.7
Requires-Dist: lxml.html
Requires-Dist: odoo (<9.0a,>=8.0a)
